multiformats/__init__.py
multiformats/py.typed
multiformats/cid/__init__.py
multiformats/multiaddr/__init__.py
multiformats/multiaddr/err.py
multiformats/multiaddr/raw.py
multiformats/multibase/__init__.py
multiformats/multibase/err.py
multiformats/multibase/raw.py
multiformats/multicodec/__init__.py
multiformats/multicodec/err.py
multiformats/multihash/__init__.py
multiformats/multihash/err.py
multiformats/multihash/raw.py
multiformats/multihash/_hashfuns/__init__.py
multiformats/multihash/_hashfuns/blake.py
multiformats/multihash/_hashfuns/filecoin.py
multiformats/multihash/_hashfuns/kangarootwelve.py
multiformats/multihash/_hashfuns/keccak.py
multiformats/multihash/_hashfuns/md.py
multiformats/multihash/_hashfuns/murmur3.py
multiformats/multihash/_hashfuns/sha.py
multiformats/multihash/_hashfuns/skein.py
multiformats/multihash/_hashfuns/utils.py
multiformats/varint/__init__.py
makkus.multiformats-0.2.4.dist-info/LICENSE
makkus.multiformats-0.2.4.dist-info/METADATA
makkus.multiformats-0.2.4.dist-info/WHEEL
makkus.multiformats-0.2.4.dist-info/top_level.txt
makkus.multiformats-0.2.4.dist-info/RECORD
